setup.py
distributions_azi/Binomialdistribution.py
distributions_azi/Gaussiandistribution.py
distributions_azi/Generaldistribution.py
distributions_azi/__init__.py
distributions_azi.egg-info/PKG-INFO
distributions_azi.egg-info/SOURCES.txt
distributions_azi.egg-info/dependency_links.txt
distributions_azi.egg-info/not-zip-safe
distributions_azi.egg-info/top_level.txt