Metadata-Version: 1.0
Name: distributions-azi
Version: 0.1
Summary: Gaussian distributions
Home-page: UNKNOWN
Author: Abdulaziz A. Hawaej
Author-email: abdulaziz602842@gmail.com
License: UNKNOWN
Platform: UNKNOWN
